fluffy_bunnies/__init__.py
fluffy_bunnies/cli.py
fluffy_bunnies/fluff.py
fluffy_bunnies/py.typed
fluffy_bunnies-0.0.1.dist-info/LICENSE
fluffy_bunnies-0.0.1.dist-info/METADATA
fluffy_bunnies-0.0.1.dist-info/WHEEL
fluffy_bunnies-0.0.1.dist-info/RECORD
