Metadata-Version: 2.1
Name: fluffy-bunnies
Version: 0.0.1
Summary: Test deployment package
Home-page: https://collijk.github.io/fluffy-bunnies
License: MIT
Author: James Collins
Author-email: collijk1@gmail.com
Requires-Python: >=3.10,<4.0
Classifier: Development Status :: 4 - Beta
Classifier: Intended Audience :: Developers
Classifier: License :: OSI Approved :: MIT License
Classifier: Operating System :: OS Independent
Classifier: Programming Language :: Python
Classifier: Programming Language :: Python :: 3
Classifier: Programming Language :: Python :: 3.10
Classifier: Programming Language :: Python :: 3.11
Classifier: Programming Language :: Python :: 3.7
Classifier: Programming Language :: Python :: 3.8
Classifier: Programming Language :: Python :: 3.9
Classifier: Topic :: Software Development :: Libraries :: Python Modules
Classifier: Typing :: Typed
Requires-Dist: click
Project-URL: Documentation, https://collijk.github.io/fluffy-bunnies
Project-URL: Repository, https://github.com/collijk/fluffy-bunnies
